[
{"270": [{"ticker_id": 9933, "pair": "BTC/USDT", "price": 9347.78, "volume_percentage": 38.377626511314226, "rank": 1}, {"ticker_id": 12306, "pair": "BCH/USDT", "price": 286.65, "volume_percentage": 6.3961695672659316, "rank": 2}, {"ticker_id": 9934, "pair": "ETH/USDT", "price": 187.01, "volume_percentage": 5.632705274188917, "rank": 3}, {"ticker_id": 22258, "pair": "TRX/USDT", "price": 0.02145, "volume_percentage": 3.3224459850902215, "rank": 4}, {"ticker_id": 12096, "pair": "BNB/USDT", "price": 20.7929, "volume_percentage": 3.139349011921224, "rank": 5}, {"ticker_id": 20945, "pair": "XRP/USDT", "price": 0.29957, "volume_percentage": 2.8437380675924517, "rank": 6}, {"ticker_id": 11894, "pair": "TRX/BTC", "price": 2.3e-06, "volume_percentage": 2.371549065870894, "rank": 7}, {"ticker_id": 9346, "pair": "ETH/BTC", "price": 0.020007, "volume_percentage": 2.142740347457508, "rank": 8}, {"ticker_id": 11975, "pair": "XRP/BTC", "price": 3.204e-05, "volume_percentage": 2.0731359063530115, "rank": 9}, {"ticker_id": 21815, "pair": "EOS/USDT", "price": 3.3518, "volume_percentage": 1.9196933049995641, "rank": 10}, {"ticker_id": 9421, "pair": "BNB/BTC", "price": 0.0022213, "volume_percentage": 1.909983394293181, "rank": 11}, {"ticker_id": 9626, "pair": "BCH/BTC", "price": 0.030656, "volume_percentage": 1.7949610914132503, "rank": 12}, {"ticker_id": 13554, "pair": "LTC/USDT", "price": 59.13, "volume_percentage": 1.436121402709346, "rank": 13}, {"ticker_id": 30688, "pair": "BTC/USDC", "price": 9358.82, "volume_percentage": 1.3486628313986733, "rank": 14}, {"ticker_id": 22254, "pair": "ONT/USDT", "price": 0.8372, "volume_percentage": 1.1484897806206271, "rank": 15}, {"ticker_id": 12644, "pair": "NEO/USDT", "price": 10.517, "volume_percentage": 1.062793618364177, "rank": 16}, {"ticker_id": 10790, "pair": "LINK/BTC", "price": 0.00028762, "volume_percentage": 0.7297818318648877, "rank": 17}, {"ticker_id": 31764, "pair": "LINK/USDT", "price": 2.6886, "volume_percentage": 0.6860376865065659, "rank": 18}, {"ticker_id": 9345, "pair": "NEO/BTC", "price": 0.001125, "volume_percentage": 0.6737229320339774, "rank": 19}, {"ticker_id": 38671, "pair": "ERD/BTC", "price": 1.8e-07, "volume_percentage": 0.6594386481844013, "rank": 20}, {"ticker_id": 30686, "pair": "USDC/USDT", "price": 0.9984, "volume_percentage": 0.6509507294115607, "rank": 21}, {"ticker_id": 18183, "pair": "ONT/BTC", "price": 8.94e-05, "volume_percentage": 0.6504376699217894, "rank": 22}, {"ticker_id": 43999, "pair": "KAVA/BTC", "price": 9.577e-05, "volume_percentage": 0.6122995494063664, "rank": 23}, {"ticker_id": 22343, "pair": "ETC/USDT", "price": 4.878, "volume_percentage": 0.6077630931433757, "rank": 24}, {"ticker_id": 11130, "pair": "EOS/BTC", "price": 0.0003582, "volume_percentage": 0.5901807284485414, "rank": 25}, {"ticker_id": 9347, "pair": "LTC/BTC", "price": 0.006328, "volume_percentage": 0.5685319510095055, "rank": 26}, {"ticker_id": 14305, "pair": "LUN/BTC", "price": 0.000129, "volume_percentage": 0.42383538583006036, "rank": 27}, {"ticker_id": 21929, "pair": "XLM/USDT", "price": 0.06639, "volume_percentage": 0.4062528253343533, "rank": 28}, {"ticker_id": 19780, "pair": "ADA/USDT", "price": 0.04285, "volume_percentage": 0.40449895901904986, "rank": 29}, {"ticker_id": 41788, "pair": "BUSD/USDT", "price": 0.9989, "volume_percentage": 0.3881848978384352, "rank": 30}, {"ticker_id": 32333, "pair": "BTT/USDT", "price": 0.0004732, "volume_percentage": 0.3842437772761396, "rank": 31}, {"ticker_id": 12275, "pair": "XMR/BTC", "price": 0.006477, "volume_percentage": 0.3656937405998579, "rank": 32}, {"ticker_id": 33664, "pair": "BTC/TUSD", "price": 9358.71, "volume_percentage": 0.3607802753437375, "rank": 33}, {"ticker_id": 44000, "pair": "KAVA/USDT", "price": 0.8901, "volume_percentage": 0.33997299637393597, "rank": 34}, {"ticker_id": 29971, "pair": "BTC/PAX", "price": 9357.11, "volume_percentage": 0.3352784651169038, "rank": 35}, {"ticker_id": 36329, "pair": "MATIC/BTC", "price": 1.51e-06, "volume_percentage": 0.2966975459696076, "rank": 36}, {"ticker_id": 13136, "pair": "ADA/BTC", "price": 4.59e-06, "volume_percentage": 0.2853843223502661, "rank": 37}, {"ticker_id": 41790, "pair": "BTC/BUSD", "price": 9355.34, "volume_percentage": 0.2850094126898259, "rank": 38}, {"ticker_id": 27298, "pair": "PAX/USDT", "price": 0.9986, "volume_percentage": 0.27841074492974155, "rank": 39}, {"ticker_id": 34052, "pair": "IOST/USDT", "price": 0.005432, "volume_percentage": 0.24942337275382004, "rank": 40}, {"ticker_id": 40668, "pair": "TOMO/BTC", "price": 3.956e-05, "volume_percentage": 0.24568952408415648, "rank": 41}, {"ticker_id": 24224, "pair": "VET/BTC", "price": 4.4e-07, "volume_percentage": 0.2405295158173889, "rank": 42}, {"ticker_id": 12274, "pair": "AMB/BTC", "price": 3.76e-06, "volume_percentage": 0.22528936485882137, "rank": 43}, {"ticker_id": 21928, "pair": "TUSD/USDT", "price": 0.9987, "volume_percentage": 0.21939091847215922, "rank": 44}, {"ticker_id": 13379, "pair": "XLM/BTC", "price": 7.1e-06, "volume_percentage": 0.2172917801520432, "rank": 45}, {"ticker_id": 41251, "pair": "CHZ/BTC", "price": 1.11e-06, "volume_percentage": 0.21301146353272116, "rank": 46}, {"ticker_id": 15076, "pair": "RLC/BTC", "price": 7.132e-05, "volume_percentage": 0.1963820814952966, "rank": 47}, {"ticker_id": 24231, "pair": "VET/USDT", "price": 0.004134, "volume_percentage": 0.18661451572825244, "rank": 48}, {"ticker_id": 11165, "pair": "ETC/BTC", "price": 0.0005216, "volume_percentage": 0.17077250518542478, "rank": 49}, {"ticker_id": 11083, "pair": "MTL/BTC", "price": 3.635e-05, "volume_percentage": 0.16885987636189137, "rank": 50}, {"ticker_id": 36332, "pair": "MATIC/USDT", "price": 0.0141, "volume_percentage": 0.16795915347924809, "rank": 51}, {"ticker_id": 11464, "pair": "DASH/BTC", "price": 0.007769, "volume_percentage": 0.16557519611760851, "rank": 52}, {"ticker_id": 39323, "pair": "DUSK/BTC", "price": 5.95e-06, "volume_percentage": 0.1526137203433735, "rank": 53}, {"ticker_id": 40669, "pair": "TOMO/USDT", "price": 0.3698, "volume_percentage": 0.14961068319563778, "rank": 54}, {"ticker_id": 12350, "pair": "BAT/BTC", "price": 2.509e-05, "volume_percentage": 0.14745834810140163, "rank": 55}, {"ticker_id": 10466, "pair": "OMG/BTC", "price": 0.000114, "volume_percentage": 0.14162695722156823, "rank": 56}, {"ticker_id": 34003, "pair": "ZEC/USDT", "price": 38.47, "volume_percentage": 0.1407959301218152, "rank": 57}, {"ticker_id": 33718, "pair": "XMR/USDT", "price": 60.5, "volume_percentage": 0.13936120737771668, "rank": 58}, {"ticker_id": 18600, "pair": "QTUM/USDT", "price": 2.278, "volume_percentage": 0.13897661643945378, "rank": 59}, {"ticker_id": 16156, "pair": "IOST/BTC", "price": 5.8e-07, "volume_percentage": 0.13550369423819453, "rank": 60}, {"ticker_id": 30687, "pair": "ETH/USDC", "price": 187.38, "volume_percentage": 0.13324743769142158, "rank": 61}, {"ticker_id": 13260, "pair": "CMT/BTC", "price": 2.11e-06, "volume_percentage": 0.1330225214913602, "rank": 62}, {"ticker_id": 13645, "pair": "WAVES/BTC", "price": 8.79e-05, "volume_percentage": 0.13128381848498202, "rank": 63}, {"ticker_id": 27709, "pair": "RVN/BTC", "price": 3.24e-06, "volume_percentage": 0.12980318976242156, "rank": 64}, {"ticker_id": 15291, "pair": "INS/BTC", "price": 2.15e-05, "volume_percentage": 0.12896402681494493, "rank": 65}, {"ticker_id": 10834, "pair": "MIOTA/BTC", "price": 3.009e-05, "volume_percentage": 0.12813091123976822, "rank": 66}, {"ticker_id": 42827, "pair": "NKN/BTC", "price": 3.15e-06, "volume_percentage": 0.12239751730083036, "rank": 67}, {"ticker_id": 22096, "pair": "QKC/BTC", "price": 5.2e-07, "volume_percentage": 0.12179950754284284, "rank": 68}, {"ticker_id": 36348, "pair": "ATOM/USDT", "price": 3.07, "volume_percentage": 0.11398739907089234, "rank": 69}, {"ticker_id": 21927, "pair": "MIOTA/USDT", "price": 0.2813, "volume_percentage": 0.11036814787573453, "rank": 70}, {"ticker_id": 11895, "pair": "TRX/ETH", "price": 0.0001148, "volume_percentage": 0.1053820623566551, "rank": 71}, {"ticker_id": 10347, "pair": "QTUM/BTC", "price": 0.0002442, "volume_percentage": 0.10509042370262021, "rank": 72}, {"ticker_id": 41696, "pair": "BAND/BTC", "price": 3.36e-05, "volume_percentage": 0.10118313030635061, "rank": 73}, {"ticker_id": 33343, "pair": "FET/BTC", "price": 4.39e-06, "volume_percentage": 0.09954650513158082, "rank": 74}, {"ticker_id": 36347, "pair": "ATOM/BTC", "price": 0.0003284, "volume_percentage": 0.0986442234221827, "rank": 75}, {"ticker_id": 10216, "pair": "WTC/BTC", "price": 8.2e-05, "volume_percentage": 0.0979772480422225, "rank": 76}, {"ticker_id": 34304, "pair": "DASH/USDT", "price": 72.63, "volume_percentage": 0.09483731417951252, "rank": 77}, {"ticker_id": 12168, "pair": "NULS/BTC", "price": 4.305e-05, "volume_percentage": 0.09340482988707453, "rank": 78}, {"ticker_id": 38297, "pair": "ALGO/USDT", "price": 0.227, "volume_percentage": 0.09280399867956907, "rank": 79}, {"ticker_id": 23750, "pair": "HOT/BTC", "price": 1e-07, "volume_percentage": 0.0914247461807062, "rank": 80}, {"ticker_id": 44005, "pair": "STX/BTC", "price": 2.291e-05, "volume_percentage": 0.0876353051273513, "rank": 81}, {"ticker_id": 33342, "pair": "FET/USDT", "price": 0.04104, "volume_percentage": 0.08682112993987022, "rank": 82}, {"ticker_id": 21869, "pair": "THETA/BTC", "price": 1.076e-05, "volume_percentage": 0.08659141126915869, "rank": 83}, {"ticker_id": 12501, "pair": "GXC/BTC", "price": 5.222e-05, "volume_percentage": 0.08336346964750299, "rank": 84}, {"ticker_id": 12382, "pair": "ZEC/BTC", "price": 0.004115, "volume_percentage": 0.08144367380470638, "rank": 85}, {"ticker_id": 39759, "pair": "WIN/USDT", "price": 0.0001615, "volume_percentage": 0.07915321620049508, "rank": 86}, {"ticker_id": 42358, "pair": "HBAR/BTC", "price": 3.7e-06, "volume_percentage": 0.07752307712352538, "rank": 87}, {"ticker_id": 9912, "pair": "BNB/ETH", "price": 0.111081, "volume_percentage": 0.07487213260333929, "rank": 88}, {"ticker_id": 38296, "pair": "ALGO/BTC", "price": 2.433e-05, "volume_percentage": 0.0744443301357848, "rank": 89}, {"ticker_id": 33388, "pair": "BAT/USDT", "price": 0.2348, "volume_percentage": 0.07340245795241074, "rank": 90}, {"ticker_id": 10515, "pair": "ZRX/BTC", "price": 3.009e-05, "volume_percentage": 0.07278532162445427, "rank": 91}, {"ticker_id": 23946, "pair": "DOCK/BTC", "price": 1.15e-06, "volume_percentage": 0.07050304821547775, "rank": 92}, {"ticker_id": 34781, "pair": "OMG/USDT", "price": 1.0676, "volume_percentage": 0.06928296722636809, "rank": 93}, {"ticker_id": 11976, "pair": "XRP/ETH", "price": 0.00160329, "volume_percentage": 0.06922295960459687, "rank": 94}, {"ticker_id": 13763, "pair": "ICX/BTC", "price": 1.796e-05, "volume_percentage": 0.06806211996240143, "rank": 95}, {"ticker_id": 31040, "pair": "TRX/XRP", "price": 0.07156, "volume_percentage": 0.06727961753073267, "rank": 96}, {"ticker_id": 9514, "pair": "EOS/ETH", "price": 0.017888, "volume_percentage": 0.06630136906813243, "rank": 97}, {"ticker_id": 9717, "pair": "GAS/BTC", "price": 0.000186, "volume_percentage": 0.0643012968331591, "rank": 98}, {"ticker_id": 26631, "pair": "TRX/BNB", "price": 0.001034, "volume_percentage": 0.06217486368142646, "rank": 99}, {"ticker_id": 18781, "pair": "WAN/BTC", "price": 2.376e-05, "volume_percentage": 0.061471021756862185, "rank": 100}, {"ticker_id": 31957, "pair": "WAVES/USDT", "price": 0.822, "volume_percentage": 0.0584387879599924, "rank": 101}, {"ticker_id": 16992, "pair": "PHX/BTC", "price": 6.7e-07, "volume_percentage": 0.056894897551982695, "rank": 102}, {"ticker_id": 22390, "pair": "ICX/USDT", "price": 0.1681, "volume_percentage": 0.05423122188036969, "rank": 103}, {"ticker_id": 21935, "pair": "XRP/BNB", "price": 0.01442, "volume_percentage": 0.053439453280274364, "rank": 104}, {"ticker_id": 22769, "pair": "NAS/BTC", "price": 6.26e-05, "volume_percentage": 0.05285921532326716, "rank": 105}, {"ticker_id": 30203, "pair": "REN/BTC", "price": 5.47e-06, "volume_percentage": 0.05270863615351861, "rank": 106}, {"ticker_id": 44006, "pair": "STX/USDT", "price": 0.2143, "volume_percentage": 0.052338477449079455, "rank": 107}, {"ticker_id": 33001, "pair": "HOT/USDT", "price": 0.000941, "volume_percentage": 0.05154543680463351, "rank": 108}, {"ticker_id": 12410, "pair": "ARN/BTC", "price": 1.985e-05, "volume_percentage": 0.050645384419459934, "rank": 109}, {"ticker_id": 39324, "pair": "DUSK/USDT", "price": 0.0557, "volume_percentage": 0.05015218305521085, "rank": 110}, {"ticker_id": 21305, "pair": "REP/BTC", "price": 0.000956, "volume_percentage": 0.0498409146933339, "rank": 111}, {"ticker_id": 16683, "pair": "NANO/BTC", "price": 9.24e-05, "volume_percentage": 0.04940836267368959, "rank": 112}, {"ticker_id": 13486, "pair": "LEND/BTC", "price": 1.53e-06, "volume_percentage": 0.04788053824376891, "rank": 113}, {"ticker_id": 38672, "pair": "ERD/USDT", "price": 0.0015954, "volume_percentage": 0.04744403180051811, "rank": 114}, {"ticker_id": 10684, "pair": "ETHOS/BTC", "price": 4.89e-06, "volume_percentage": 0.046922397845815, "rank": 115}, {"ticker_id": 10106, "pair": "MCO/BTC", "price": 0.0004632, "volume_percentage": 0.0462960623307092, "rank": 116}, {"ticker_id": 33663, "pair": "ETH/TUSD", "price": 187.12, "volume_percentage": 0.04579969759102699, "rank": 117}, {"ticker_id": 10952, "pair": "MDA/BTC", "price": 7.878e-05, "volume_percentage": 0.04272609609502746, "rank": 118}, {"ticker_id": 13488, "pair": "WABI/BTC", "price": 1.676e-05, "volume_percentage": 0.0424528513057372, "rank": 119}, {"ticker_id": 32038, "pair": "BCH/TUSD", "price": 287.02, "volume_percentage": 0.041779529455601816, "rank": 120}, {"ticker_id": 37404, "pair": "TFUEL/BTC", "price": 3.9e-07, "volume_percentage": 0.04158118424679903, "rank": 121}, {"ticker_id": 14009, "pair": "ELF/BTC", "price": 9.49e-06, "volume_percentage": 0.04066115355262661, "rank": 122}, {"ticker_id": 34076, "pair": "CELR/USDT", "price": 0.00423, "volume_percentage": 0.04039538964637231, "rank": 123}, {"ticker_id": 39928, "pair": "COS/BTC", "price": 1.72e-06, "volume_percentage": 0.039177181742332645, "rank": 124}, {"ticker_id": 41697, "pair": "BAND/USDT", "price": 0.314, "volume_percentage": 0.03840970323118251, "rank": 125}, {"ticker_id": 10792, "pair": "NEO/ETH", "price": 0.056272, "volume_percentage": 0.0384005285812508, "rank": 126}, {"ticker_id": 40712, "pair": "PERL/BTC", "price": 3.06e-06, "volume_percentage": 0.03839740514316757, "rank": 127}, {"ticker_id": 34075, "pair": "CELR/BTC", "price": 4.5e-07, "volume_percentage": 0.037918231880024064, "rank": 128}, {"ticker_id": 29970, "pair": "ETH/PAX", "price": 187.11, "volume_percentage": 0.037794827075442045, "rank": 129}, {"ticker_id": 20555, "pair": "LOOM/BTC", "price": 2.48e-06, "volume_percentage": 0.03748705048971836, "rank": 130}, {"ticker_id": 32039, "pair": "BCH/USDC", "price": 287.02, "volume_percentage": 0.03719341698414837, "rank": 131}, {"ticker_id": 29463, "pair": "MITH/BTC", "price": 1.43e-06, "volume_percentage": 0.03705122994005892, "rank": 132}, {"ticker_id": 10764, "pair": "SNM/BTC", "price": 1.31e-06, "volume_percentage": 0.036787051905420115, "rank": 133}, {"ticker_id": 33238, "pair": "ZRX/USDT", "price": 0.2814, "volume_percentage": 0.036350089457344026, "rank": 134}, {"ticker_id": 10789, "pair": "LINK/ETH", "price": 0.0143629, "volume_percentage": 0.035925849361837944, "rank": 135}, {"ticker_id": 32037, "pair": "LTC/USDC", "price": 59.46, "volume_percentage": 0.03543887582138413, "rank": 136}, {"ticker_id": 12794, "pair": "FUEL/BTC", "price": 3.8e-07, "volume_percentage": 0.03543632386149063, "rank": 137}, {"ticker_id": 41252, "pair": "CHZ/USDT", "price": 0.010316, "volume_percentage": 0.03506287608106616, "rank": 138}, {"ticker_id": 43460, "pair": "BCH/BUSD", "price": 287.13, "volume_percentage": 0.03504587671808137, "rank": 139}, {"ticker_id": 42828, "pair": "NKN/USDT", "price": 0.02955, "volume_percentage": 0.034174550943192494, "rank": 140}, {"ticker_id": 18030, "pair": "ZIL/BTC", "price": 6e-07, "volume_percentage": 0.03345533843462351, "rank": 141}, {"ticker_id": 30690, "pair": "BNB/USDC", "price": 20.7582, "volume_percentage": 0.03260134183533526, "rank": 142}, {"ticker_id": 37615, "pair": "ONE/BTC", "price": 5.6e-07, "volume_percentage": 0.03248075753736325, "rank": 143}, {"ticker_id": 10000, "pair": "HC/BTC", "price": 0.0001887, "volume_percentage": 0.03138141292482356, "rank": 144}, {"ticker_id": 30685, "pair": "XRP/USDC", "price": 0.29927, "volume_percentage": 0.030039606740115743, "rank": 145}, {"ticker_id": 37406, "pair": "TFUEL/USDT", "price": 0.00364, "volume_percentage": 0.030022503155205566, "rank": 146}, {"ticker_id": 18628, "pair": "XEM/BTC", "price": 4.52e-06, "volume_percentage": 0.02934722090107693, "rank": 147}, {"ticker_id": 38690, "pair": "DOGE/USDT", "price": 0.0026466, "volume_percentage": 0.028388218533014695, "rank": 148}, {"ticker_id": 23665, "pair": "NULS/USDT", "price": 0.4026, "volume_percentage": 0.027253610800990705, "rank": 149}, {"ticker_id": 41791, "pair": "BNB/BUSD", "price": 20.7759, "volume_percentage": 0.026491565103959072, "rank": 150}, {"ticker_id": 32989, "pair": "ONG/BTC", "price": 1.772e-05, "volume_percentage": 0.025665052893231177, "rank": 151}, {"ticker_id": 12277, "pair": "DLT/BTC", "price": 4.43e-06, "volume_percentage": 0.02561087385548108, "rank": 152}, {"ticker_id": 40614, "pair": "MTL/USDT", "price": 0.3405, "volume_percentage": 0.025602534809143703, "rank": 153}, {"ticker_id": 37620, "pair": "ONE/USDT", "price": 0.0053, "volume_percentage": 0.02556226475149114, "rank": 154}, {"ticker_id": 44001, "pair": "KAVA/BNB", "price": 0.04274, "volume_percentage": 0.024981334410638118, "rank": 155}, {"ticker_id": 16851, "pair": "AE/BTC", "price": 2.36e-05, "volume_percentage": 0.024921110513451254, "rank": 156}, {"ticker_id": 21816, "pair": "EOS/BNB", "price": 0.1611, "volume_percentage": 0.024800924816646516, "rank": 157}, {"ticker_id": 19278, "pair": "GRS/BTC", "price": 2.357e-05, "volume_percentage": 0.024159298853986426, "rank": 158}, {"ticker_id": 33046, "pair": "ZIL/USDT", "price": 0.00553, "volume_percentage": 0.02408994460810057, "rank": 159}, {"ticker_id": 38689, "pair": "DOGE/BTC", "price": 2.9e-07, "volume_percentage": 0.024077485956983, "rank": 160}, {"ticker_id": 35665, "pair": "THETA/USDT", "price": 0.1012, "volume_percentage": 0.023814508397087313, "rank": 161}, {"ticker_id": 12374, "pair": "BCPT/BTC", "price": 3.22e-06, "volume_percentage": 0.023454387750692265, "rank": 162}, {"ticker_id": 18182, "pair": "ONT/ETH", "price": 0.004473, "volume_percentage": 0.022831285861316084, "rank": 163}, {"ticker_id": 43458, "pair": "ETH/BUSD", "price": 187.17, "volume_percentage": 0.022513127784258243, "rank": 164}, {"ticker_id": 43455, "pair": "XRP/BUSD", "price": 0.29998, "volume_percentage": 0.022146710239326874, "rank": 165}, {"ticker_id": 37937, "pair": "FTM/BTC", "price": 1.29e-06, "volume_percentage": 0.02208660407518381, "rank": 166}, {"ticker_id": 12002, "pair": "ENJ/BTC", "price": 6.8e-06, "volume_percentage": 0.022014097595967733, "rank": 167}, {"ticker_id": 13163, "pair": "PPT/BTC", "price": 5.81e-05, "volume_percentage": 0.021843547493321354, "rank": 168}, {"ticker_id": 41806, "pair": "BEAM/BTC", "price": 6.33e-05, "volume_percentage": 0.021542592166256796, "rank": 169}, {"ticker_id": 12750, "pair": "TNT/BTC", "price": 7.34e-06, "volume_percentage": 0.021165793516482824, "rank": 170}, {"ticker_id": 11531, "pair": "OAX/BTC", "price": 7.76e-06, "volume_percentage": 0.020964865652676763, "rank": 171}, {"ticker_id": 41849, "pair": "XTZ/BTC", "price": 9.04e-05, "volume_percentage": 0.020622427127633836, "rank": 172}, {"ticker_id": 42359, "pair": "HBAR/USDT", "price": 0.03451, "volume_percentage": 0.020497720611679825, "rank": 173}, {"ticker_id": 43456, "pair": "LTC/BUSD", "price": 59.26, "volume_percentage": 0.019645212590610157, "rank": 174}, {"ticker_id": 42196, "pair": "RVN/USDT", "price": 0.03014, "volume_percentage": 0.019571190852981223, "rank": 175}, {"ticker_id": 12016, "pair": "STORJ/BTC", "price": 1.518e-05, "volume_percentage": 0.01950151043840404, "rank": 176}, {"ticker_id": 12448, "pair": "GVT/BTC", "price": 0.0001204, "volume_percentage": 0.019463779008691694, "rank": 177}, {"ticker_id": 32040, "pair": "BCH/PAX", "price": 291.16, "volume_percentage": 0.01936106116019247, "rank": 178}, {"ticker_id": 10872, "pair": "XVG/BTC", "price": 4e-07, "volume_percentage": 0.01925315907686511, "rank": 179}, {"ticker_id": 13261, "pair": "CMT/ETH", "price": 0.00010588, "volume_percentage": 0.01899917645172275, "rank": 180}, {"ticker_id": 23457, "pair": "ARDR/BTC", "price": 5.89e-06, "volume_percentage": 0.01888077265434398, "rank": 181}, {"ticker_id": 24225, "pair": "VET/ETH", "price": 2.213e-05, "volume_percentage": 0.018753071151591715, "rank": 182}, {"ticker_id": 11675, "pair": "EVX/BTC", "price": 3.692e-05, "volume_percentage": 0.018690077744080894, "rank": 183}, {"ticker_id": 12755, "pair": "LSK/BTC", "price": 8.5e-05, "volume_percentage": 0.018457075433475297, "rank": 184}, {"ticker_id": 41807, "pair": "BEAM/USDT", "price": 0.594, "volume_percentage": 0.018384489773900902, "rank": 185}, {"ticker_id": 11836, "pair": "VIB/BTC", "price": 2.52e-06, "volume_percentage": 0.018273987954195686, "rank": 186}, {"ticker_id": 40562, "pair": "COCOS/USDT", "price": 0.000948, "volume_percentage": 0.018110185809152732, "rank": 187}, {"ticker_id": 41137, "pair": "WIN/TRX", "price": 0.00753, "volume_percentage": 0.017929923902368142, "rank": 188}, {"ticker_id": 16058, "pair": "PIVX/BTC", "price": 2.619e-05, "volume_percentage": 0.017765610728845027, "rank": 189}, {"ticker_id": 30362, "pair": "XRP/TUSD", "price": 0.3, "volume_percentage": 0.017650076057434246, "rank": 190}, {"ticker_id": 11926, "pair": "ARK/BTC", "price": 2.225e-05, "volume_percentage": 0.017538899838326242, "rank": 191}, {"ticker_id": 29972, "pair": "BNB/PAX", "price": 20.8042, "volume_percentage": 0.01751002685116621, "rank": 192}, {"ticker_id": 23751, "pair": "HOT/ETH", "price": 5.02e-06, "volume_percentage": 0.01724509704915187, "rank": 193}, {"ticker_id": 12646, "pair": "NEO/BNB", "price": 0.5082, "volume_percentage": 0.017150434775770714, "rank": 194}, {"ticker_id": 11609, "pair": "BTG/BTC", "price": 0.000885, "volume_percentage": 0.016860743257272225, "rank": 195}, {"ticker_id": 26149, "pair": "GO/BTC", "price": 9.1e-07, "volume_percentage": 0.016724721500675246, "rank": 196}, {"ticker_id": 31512, "pair": "USDC/TUSD", "price": 1.0004, "volume_percentage": 0.01624259000731968, "rank": 197}, {"ticker_id": 32033, "pair": "TRX/USDC", "price": 0.02148, "volume_percentage": 0.016086146535670413, "rank": 198}, {"ticker_id": 12175, "pair": "RDN/BTC", "price": 1.717e-05, "volume_percentage": 0.015818094198274627, "rank": 199}, {"ticker_id": 30776, "pair": "TRX/TUSD", "price": 0.02148, "volume_percentage": 0.0158090694708264, "rank": 200}, {"ticker_id": 40714, "pair": "PERL/USDT", "price": 0.02861, "volume_percentage": 0.015685544179764012, "rank": 201}, {"ticker_id": 42198, "pair": "HC/USDT", "price": 1.7574, "volume_percentage": 0.015586234826779751, "rank": 202}, {"ticker_id": 11166, "pair": "ETC/ETH", "price": 0.026121, "volume_percentage": 0.01553399481356233, "rank": 203}, {"ticker_id": 13137, "pair": "ADA/ETH", "price": 0.00022881, "volume_percentage": 0.015352670069605254, "rank": 204}, {"ticker_id": 18985, "pair": "SYS/BTC", "price": 2.65e-06, "volume_percentage": 0.015207691104090246, "rank": 205}, {"ticker_id": 10835, "pair": "MIOTA/ETH", "price": 0.00150633, "volume_percentage": 0.014854565411704594, "rank": 206}, {"ticker_id": 22403, "pair": "SC/BTC", "price": 2.2e-07, "volume_percentage": 0.014423951632836047, "rank": 207}, {"ticker_id": 12160, "pair": "RCN/BTC", "price": 4.24e-06, "volume_percentage": 0.014701060089163397, "rank": 208}, {"ticker_id": 13553, "pair": "LTC/ETH", "price": 0.3165, "volume_percentage": 0.014579837513687598, "rank": 209}, {"ticker_id": 13555, "pair": "LTC/BNB", "price": 2.852, "volume_percentage": 0.014312823093570863, "rank": 210}, {"ticker_id": 11717, "pair": "REQ/BTC", "price": 1.48e-06, "volume_percentage": 0.014153362859639867, "rank": 211}, {"ticker_id": 10527, "pair": "STRAT/BTC", "price": 3.51e-05, "volume_percentage": 0.014052350460811469, "rank": 212}, {"ticker_id": 11184, "pair": "MTH/BTC", "price": 1.57e-06, "volume_percentage": 0.013938095683288255, "rank": 213}, {"ticker_id": 11164, "pair": "SNT/BTC", "price": 1.39e-06, "volume_percentage": 0.013934891772450093, "rank": 214}, {"ticker_id": 19022, "pair": "WPR/BTC", "price": 8.3e-07, "volume_percentage": 0.0139253991469479, "rank": 215}, {"ticker_id": 15077, "pair": "RLC/ETH", "price": 0.003605, "volume_percentage": 0.013541159506681168, "rank": 216}, {"ticker_id": 41850, "pair": "XTZ/USDT", "price": 0.8527, "volume_percentage": 0.013341223110695235, "rank": 217}, {"ticker_id": 18184, "pair": "ONT/BNB", "price": 0.04025, "volume_percentage": 0.01330592118868257, "rank": 218}, {"ticker_id": 41136, "pair": "BTT/TRX", "price": 0.02204, "volume_percentage": 0.013179792780358522, "rank": 219}, {"ticker_id": 13974, "pair": "AION/BTC", "price": 8.33e-06, "volume_percentage": 0.01311410451003474, "rank": 220}, {"ticker_id": 40729, "pair": "WAN/USDT", "price": 0.222, "volume_percentage": 0.012920780511125749, "rank": 221}, {"ticker_id": 11183, "pair": "ENG/BTC", "price": 3.222e-05, "volume_percentage": 0.012756913831160066, "rank": 222}, {"ticker_id": 14028, "pair": "NEBL/BTC", "price": 5.309e-05, "volume_percentage": 0.012609216614508463, "rank": 223}, {"ticker_id": 12121, "pair": "KMD/BTC", "price": 6.1e-05, "volume_percentage": 0.012557981729700157, "rank": 224}, {"ticker_id": 22098, "pair": "AGI/BTC", "price": 2.32e-06, "volume_percentage": 0.012497563881451172, "rank": 225}, {"ticker_id": 34780, "pair": "NANO/USDT", "price": 0.8685, "volume_percentage": 0.012473129018096172, "rank": 226}, {"ticker_id": 31510, "pair": "USDC/PAX", "price": 0.9996, "volume_percentage": 0.011987431981938773, "rank": 227}, {"ticker_id": 11360, "pair": "BNT/BTC", "price": 3.52e-05, "volume_percentage": 0.011770365443676517, "rank": 228}, {"ticker_id": 12351, "pair": "BAT/ETH", "price": 0.0012604, "volume_percentage": 0.011689595728339875, "rank": 229}, {"ticker_id": 12682, "pair": "QSP/BTC", "price": 1.33e-06, "volume_percentage": 0.011595018247183814, "rank": 230}, {"ticker_id": 30689, "pair": "EOS/USDC", "price": 3.3529, "volume_percentage": 0.01155668357290166, "rank": 231}, {"ticker_id": 33000, "pair": "ONG/USDT", "price": 0.1655, "volume_percentage": 0.011433862796521642, "rank": 232}, {"ticker_id": 16627, "pair": "STEEM/BTC", "price": 1.552e-05, "volume_percentage": 0.011406110850131183, "rank": 233}, {"ticker_id": 32330, "pair": "BTT/BNB", "price": 2.277e-05, "volume_percentage": 0.01140386991956513, "rank": 234}, {"ticker_id": 20368, "pair": "GNT/BTC", "price": 5.04e-06, "volume_percentage": 0.011317202891889413, "rank": 235}, {"ticker_id": 9512, "pair": "QTUM/ETH", "price": 0.012205, "volume_percentage": 0.011059877430029045, "rank": 236}, {"ticker_id": 14910, "pair": "VIBE/BTC", "price": 1.95e-06, "volume_percentage": 0.01098729204127423, "rank": 237}, {"ticker_id": 13381, "pair": "XLM/ETH", "price": 0.00035549, "volume_percentage": 0.010983836951250978, "rank": 238}, {"ticker_id": 34006, "pair": "ZEC/USDC", "price": 38.54, "volume_percentage": 0.010963846329447831, "rank": 239}, {"ticker_id": 10327, "pair": "LRC/BTC", "price": 3.63e-06, "volume_percentage": 0.01081201311472422, "rank": 240}, {"ticker_id": 34245, "pair": "NEO/USDC", "price": 10.526, "volume_percentage": 0.010747623178304268, "rank": 241}, {"ticker_id": 12696, "pair": "BTS/BTC", "price": 3.13e-06, "volume_percentage": 0.010616713904634553, "rank": 242}, {"ticker_id": 12752, "pair": "XZC/BTC", "price": 0.0005416, "volume_percentage": 0.010615999822303759, "rank": 243}, {"ticker_id": 40667, "pair": "TOMO/BNB", "price": 0.0178, "volume_percentage": 0.010598705916183669, "rank": 244}, {"ticker_id": 13106, "pair": "ADX/BTC", "price": 8.69e-06, "volume_percentage": 0.010588392451315504, "rank": 245}, {"ticker_id": 32035, "pair": "TRX/PAX", "price": 0.02149, "volume_percentage": 0.010370647853149534, "rank": 246}, {"ticker_id": 21817, "pair": "CVC/BTC", "price": 4.57e-06, "volume_percentage": 0.01026179400209881, "rank": 247}, {"ticker_id": 24050, "pair": "POLY/BTC", "price": 2.78e-06, "volume_percentage": 0.010255431693717659, "rank": 248}, {"ticker_id": 38670, "pair": "ERD/BNB", "price": 7.648e-05, "volume_percentage": 0.01023497699586291, "rank": 249}, {"ticker_id": 18031, "pair": "ZIL/ETH", "price": 2.955e-05, "volume_percentage": 0.010168055662542428, "rank": 250}, {"ticker_id": 22742, "pair": "KEY/BTC", "price": 1.5e-07, "volume_percentage": 0.0100472973736706, "rank": 251}, {"ticker_id": 28516, "pair": "DCR/BTC", "price": 0.001643, "volume_percentage": 0.01002593791210867, "rank": 252}, {"ticker_id": 29967, "pair": "XRP/PAX", "price": 0.29973, "volume_percentage": 0.010007564705821825, "rank": 253}, {"ticker_id": 40561, "pair": "COCOS/BTC", "price": 1e-07, "volume_percentage": 0.009930639857373871, "rank": 254}, {"ticker_id": 18901, "pair": "QLC/BTC", "price": 2.02e-06, "volume_percentage": 0.009851739351027664, "rank": 255}, {"ticker_id": 12947, "pair": "MANA/BTC", "price": 3.39e-06, "volume_percentage": 0.009545968794455543, "rank": 256}, {"ticker_id": 11716, "pair": "REQ/ETH", "price": 7.477e-05, "volume_percentage": 0.009519434985466795, "rank": 257}, {"ticker_id": 16830, "pair": "VIA/BTC", "price": 2.158e-05, "volume_percentage": 0.009447762273481236, "rank": 258}, {"ticker_id": 16157, "pair": "IOST/ETH", "price": 2.909e-05, "volume_percentage": 0.00925663679009897, "rank": 259}, {"ticker_id": 18780, "pair": "WAN/BNB", "price": 0.0107, "volume_percentage": 0.009217562662905812, "rank": 260}, {"ticker_id": 40195, "pair": "NPXS/USDT", "price": 0.0001796, "volume_percentage": 0.009143604280087397, "rank": 261}, {"ticker_id": 24226, "pair": "VET/BNB", "price": 0.0001993, "volume_percentage": 0.009102531638985133, "rank": 262}, {"ticker_id": 37409, "pair": "TFUEL/BNB", "price": 0.0001751, "volume_percentage": 0.008966569188558798, "rank": 263}, {"ticker_id": 13646, "pair": "WAVES/ETH", "price": 0.004398, "volume_percentage": 0.00889275847066631, "rank": 264}, {"ticker_id": 40732, "pair": "DOCK/USDT", "price": 0.010806, "volume_percentage": 0.008882215515429929, "rank": 265}, {"ticker_id": 10748, "pair": "KNC/BTC", "price": 1.933e-05, "volume_percentage": 0.008850745293679522, "rank": 266}, {"ticker_id": 21719, "pair": "ZEN/BTC", "price": 0.0004962, "volume_percentage": 0.008834066418645294, "rank": 267}, {"ticker_id": 12281, "pair": "XMR/ETH", "price": 0.32456, "volume_percentage": 0.008756938723955915, "rank": 268}, {"ticker_id": 17755, "pair": "POA/BTC", "price": 1.79e-06, "volume_percentage": 0.008549991635665097, "rank": 269}, {"ticker_id": 22146, "pair": "NXS/BTC", "price": 3.444e-05, "volume_percentage": 0.008465663528935739, "rank": 270}, {"ticker_id": 31511, "pair": "PAX/TUSD", "price": 1.0003, "volume_percentage": 0.008195179169670401, "rank": 271}, {"ticker_id": 13085, "pair": "MIOTA/BNB", "price": 0.01352, "volume_percentage": 0.008129851188661967, "rank": 272}, {"ticker_id": 32036, "pair": "LTC/TUSD", "price": 59.22, "volume_percentage": 0.00811937928165691, "rank": 273}, {"ticker_id": 36331, "pair": "MATIC/BNB", "price": 0.0006822, "volume_percentage": 0.008087180931823009, "rank": 274}, {"ticker_id": 36026, "pair": "MITH/USDT", "price": 0.01345, "volume_percentage": 0.00795140852710923, "rank": 275}, {"ticker_id": 11266, "pair": "DNT/BTC", "price": 6.8e-07, "volume_percentage": 0.007875967056045466, "rank": 276}, {"ticker_id": 13838, "pair": "OST/BTC", "price": 1.25e-06, "volume_percentage": 0.0078055305859257625, "rank": 277}, {"ticker_id": 14143, "pair": "EDO/BTC", "price": 3.183e-05, "volume_percentage": 0.007633672290121452, "rank": 278}, {"ticker_id": 11102, "pair": "MTL/ETH", "price": 0.001819, "volume_percentage": 0.007562667554003621, "rank": 279}, {"ticker_id": 39927, "pair": "COS/USDT", "price": 0.01611, "volume_percentage": 0.007464029540888112, "rank": 280}, {"ticker_id": 15290, "pair": "INS/ETH", "price": 0.001074, "volume_percentage": 0.007426595688513879, "rank": 281}, {"ticker_id": 14116, "pair": "BRD/BTC", "price": 3.599e-05, "volume_percentage": 0.007424041622541109, "rank": 282}, {"ticker_id": 11435, "pair": "AST/BTC", "price": 2.69e-06, "volume_percentage": 0.007229082910112398, "rank": 283}, {"ticker_id": 21306, "pair": "REP/ETH", "price": 0.04796, "volume_percentage": 0.007084237361864552, "rank": 284}, {"ticker_id": 39757, "pair": "WIN/BNB", "price": 7.78e-06, "volume_percentage": 0.00697631777880883, "rank": 285}, {"ticker_id": 33665, "pair": "BNB/TUSD", "price": 20.8094, "volume_percentage": 0.006644106758401213, "rank": 286}, {"ticker_id": 43459, "pair": "ETC/BUSD", "price": 4.8707, "volume_percentage": 0.0066295414592565495, "rank": 287}, {"ticker_id": 37938, "pair": "FTM/USDT", "price": 0.01211, "volume_percentage": 0.006600786559100395, "rank": 288}, {"ticker_id": 21738, "pair": "SKY/BTC", "price": 6.931e-05, "volume_percentage": 0.006508383401456087, "rank": 289}, {"ticker_id": 21870, "pair": "THETA/ETH", "price": 0.00053961, "volume_percentage": 0.006504214244381944, "rank": 290}, {"ticker_id": 22608, "pair": "NPXS/ETH", "price": 9.6e-07, "volume_percentage": 0.006467596437945955, "rank": 291}, {"ticker_id": 42197, "pair": "REN/USDT", "price": 0.05111, "volume_percentage": 0.006451667390489865, "rank": 292}, {"ticker_id": 10579, "pair": "SNGLS/BTC", "price": 9.8e-07, "volume_percentage": 0.006442440594922514, "rank": 293}, {"ticker_id": 10468, "pair": "OMG/ETH", "price": 0.005731, "volume_percentage": 0.0062341101464292335, "rank": 294}, {"ticker_id": 11465, "pair": "DASH/ETH", "price": 0.38863, "volume_percentage": 0.006225763394063894, "rank": 295}, {"ticker_id": 12278, "pair": "AMB/ETH", "price": 0.00019025, "volume_percentage": 0.006202068684036277, "rank": 296}, {"ticker_id": 38295, "pair": "ALGO/BNB", "price": 0.01093, "volume_percentage": 0.006184052537716513, "rank": 297}, {"ticker_id": 11950, "pair": "POWR/BTC", "price": 5.07e-06, "volume_percentage": 0.006182372856142734, "rank": 298}, {"ticker_id": 39611, "pair": "ONT/USDC", "price": 0.8368, "volume_percentage": 0.006134561879646069, "rank": 299}, {"ticker_id": 19781, "pair": "ADA/BNB", "price": 0.002062, "volume_percentage": 0.006018349034591504, "rank": 300}, {"ticker_id": 10338, "pair": "YOYOW/BTC", "price": 1.36e-06, "volume_percentage": 0.005990573990368521, "rank": 301}, {"ticker_id": 23038, "pair": "DENT/ETH", "price": 1.29e-06, "volume_percentage": 0.005953942980413406, "rank": 302}, {"ticker_id": 12642, "pair": "POE/BTC", "price": 2.6e-07, "volume_percentage": 0.005863259714506434, "rank": 303}, {"ticker_id": 13769, "pair": "GTO/BTC", "price": 1.31e-06, "volume_percentage": 0.005849970578644013, "rank": 304}, {"ticker_id": 10791, "pair": "FUN/BTC", "price": 3.5e-07, "volume_percentage": 0.005839539059512835, "rank": 305}, {"ticker_id": 41253, "pair": "CHZ/BNB", "price": 0.0004955, "volume_percentage": 0.0058239036067490955, "rank": 306}, {"ticker_id": 40736, "pair": "KEY/USDT", "price": 0.001382, "volume_percentage": 0.00578307382779554, "rank": 307}, {"ticker_id": 12970, "pair": "BCD/BTC", "price": 5.546e-05, "volume_percentage": 0.005735523672572863, "rank": 308}, {"ticker_id": 10749, "pair": "KNC/ETH", "price": 0.0009667, "volume_percentage": 0.0055690396603424895, "rank": 309}, {"ticker_id": 22342, "pair": "ETC/BNB", "price": 0.2346, "volume_percentage": 0.005522098913825113, "rank": 310}, {"ticker_id": 39326, "pair": "DUSK/USDC", "price": 0.056, "volume_percentage": 0.005496379948338594, "rank": 311}, {"ticker_id": 14701, "pair": "APPC/BTC", "price": 4.19e-06, "volume_percentage": 0.005443899081003269, "rank": 312}, {"ticker_id": 39760, "pair": "WIN/USDC", "price": 0.0001619, "volume_percentage": 0.005329403998057055, "rank": 313}, {"ticker_id": 21975, "pair": "IOTX/BTC", "price": 4.4e-07, "volume_percentage": 0.005221955163957955, "rank": 314}, {"ticker_id": 38298, "pair": "ALGO/TUSD", "price": 0.228, "volume_percentage": 0.005174311757208575, "rank": 315}, {"ticker_id": 32034, "pair": "LTC/PAX", "price": 59.63, "volume_percentage": 0.00504600218601937, "rank": 316}, {"ticker_id": 18782, "pair": "WAN/ETH", "price": 0.001188, "volume_percentage": 0.004982421828942122, "rank": 317}, {"ticker_id": 10516, "pair": "ZRX/ETH", "price": 0.00150801, "volume_percentage": 0.004951351571952722, "rank": 318}, {"ticker_id": 35990, "pair": "ENJ/USDT", "price": 0.06386, "volume_percentage": 0.004894084378138376, "rank": 319}, {"ticker_id": 30774, "pair": "NEO/TUSD", "price": 10.547, "volume_percentage": 0.004724905636054141, "rank": 320}, {"ticker_id": 31765, "pair": "LINK/USDC", "price": 2.69, "volume_percentage": 0.004709889974978797, "rank": 321}, {"ticker_id": 20557, "pair": "LOOM/ETH", "price": 0.00012395, "volume_percentage": 0.004695093678593937, "rank": 322}, {"ticker_id": 16813, "pair": "BLZ/BTC", "price": 2.79e-06, "volume_percentage": 0.004613172773461032, "rank": 323}, {"ticker_id": 13380, "pair": "XLM/BNB", "price": 0.003192, "volume_percentage": 0.0046126367602457976, "rank": 324}, {"ticker_id": 39371, "pair": "ANKR/BTC", "price": 2.5e-07, "volume_percentage": 0.004576775882126446, "rank": 325}, {"ticker_id": 14237, "pair": "NAV/BTC", "price": 1.036e-05, "volume_percentage": 0.004547093408383892, "rank": 326}, {"ticker_id": 13060, "pair": "DGD/BTC", "price": 0.001315, "volume_percentage": 0.004568151436100991, "rank": 327}, {"ticker_id": 15075, "pair": "RLC/BNB", "price": 0.03237, "volume_percentage": 0.0044514431861610365, "rank": 328}, {"ticker_id": 39327, "pair": "DUSK/BNB", "price": 0.0027, "volume_percentage": 0.004362205940156118, "rank": 329}, {"ticker_id": 40733, "pair": "DENT/USDT", "price": 0.0002431, "volume_percentage": 0.004304702686892392, "rank": 330}, {"ticker_id": 12502, "pair": "GXC/ETH", "price": 0.002609, "volume_percentage": 0.004252472359510917, "rank": 331}, {"ticker_id": 10217, "pair": "WTC/ETH", "price": 0.004094, "volume_percentage": 0.004090732920015599, "rank": 332}, {"ticker_id": 13764, "pair": "ICX/ETH", "price": 0.000892, "volume_percentage": 0.004076039541835116, "rank": 333}, {"ticker_id": 39612, "pair": "ONT/PAX", "price": 0.8374, "volume_percentage": 0.004028307339549622, "rank": 334}, {"ticker_id": 39325, "pair": "DUSK/PAX", "price": 0.056, "volume_percentage": 0.003979917841119946, "rank": 335}, {"ticker_id": 32595, "pair": "BTC/USDS", "price": 9394.38, "volume_percentage": 0.0039731195261002794, "rank": 336}, {"ticker_id": 34074, "pair": "CELR/BNB", "price": 0.0002036, "volume_percentage": 0.0038967496923426035, "rank": 337}, {"ticker_id": 33719, "pair": "XMR/BNB", "price": 2.913, "volume_percentage": 0.0038917111028399804, "rank": 338}, {"ticker_id": 13421, "pair": "CND/BTC", "price": 7.9e-07, "volume_percentage": 0.003858161707075797, "rank": 339}, {"ticker_id": 11837, "pair": "VIB/ETH", "price": 0.00012686, "volume_percentage": 0.0038514945194591524, "rank": 340}, {"ticker_id": 29969, "pair": "EOS/PAX", "price": 3.3599, "volume_percentage": 0.0038319535767822066, "rank": 341}, {"ticker_id": 22770, "pair": "NAS/ETH", "price": 0.003122, "volume_percentage": 0.003813403544623922, "rank": 342}, {"ticker_id": 37617, "pair": "ONE/BNB", "price": 0.0002568, "volume_percentage": 0.0037571484485344965, "rank": 343}, {"ticker_id": 12450, "pair": "CDT/BTC", "price": 1.38e-06, "volume_percentage": 0.0036965733513635406, "rank": 344}, {"ticker_id": 34244, "pair": "ADA/USDC", "price": 0.04289, "volume_percentage": 0.0036497941229814844, "rank": 345}, {"ticker_id": 22097, "pair": "QKC/ETH", "price": 2.624e-05, "volume_percentage": 0.0035919197323925414, "rank": 346}, {"ticker_id": 32945, "pair": "BTT/USDC", "price": 0.0004742, "volume_percentage": 0.0035838777373658785, "rank": 347}, {"ticker_id": 34053, "pair": "IOST/BNB", "price": 0.0002613, "volume_percentage": 0.0035216176731450244, "rank": 348}, {"ticker_id": 11676, "pair": "EVX/ETH", "price": 0.0018527, "volume_percentage": 0.0034615140660029355, "rank": 349}, {"ticker_id": 12411, "pair": "ARN/ETH", "price": 0.00099834, "volume_percentage": 0.003437104959568624, "rank": 350}, {"ticker_id": 34782, "pair": "OMG/BNB", "price": 0.05159, "volume_percentage": 0.0033998270288861016, "rank": 351}, {"ticker_id": 13973, "pair": "AION/ETH", "price": 0.000415, "volume_percentage": 0.003342911327017617, "rank": 352}, {"ticker_id": 13485, "pair": "LEND/ETH", "price": 7.65e-05, "volume_percentage": 0.0032726704536528684, "rank": 353}, {"ticker_id": 22404, "pair": "SC/ETH", "price": 1.074e-05, "volume_percentage": 0.0032432211074994366, "rank": 354}, {"ticker_id": 22219, "pair": "DATA/BTC", "price": 1.34e-06, "volume_percentage": 0.0032114253207582563, "rank": 355}, {"ticker_id": 12349, "pair": "BAT/BNB", "price": 0.01134, "volume_percentage": 0.0032079562398958663, "rank": 356}, {"ticker_id": 39374, "pair": "ANKR/USDT", "price": 0.002263, "volume_percentage": 0.0031642154868025208, "rank": 357}, {"ticker_id": 10078, "pair": "MCO/ETH", "price": 0.023226, "volume_percentage": 0.003107339471765049, "rank": 358}, {"ticker_id": 36349, "pair": "ATOM/BNB", "price": 0.1478, "volume_percentage": 0.002952036594928022, "rank": 359}, {"ticker_id": 32910, "pair": "USDS/USDC", "price": 0.9989, "volume_percentage": 0.002906014861341988, "rank": 360}, {"ticker_id": 9513, "pair": "SNT/ETH", "price": 6.959e-05, "volume_percentage": 0.0028213956453704203, "rank": 361}, {"ticker_id": 10957, "pair": "MDA/ETH", "price": 0.0039219, "volume_percentage": 0.0028099739092931823, "rank": 362}, {"ticker_id": 12003, "pair": "ENJ/ETH", "price": 0.00034091, "volume_percentage": 0.0027753200825575467, "rank": 363}, {"ticker_id": 34305, "pair": "DASH/BNB", "price": 3.475, "volume_percentage": 0.002748868225500863, "rank": 364}, {"ticker_id": 22957, "pair": "MFT/BTC", "price": 1.1e-07, "volume_percentage": 0.002713607615239481, "rank": 365}, {"ticker_id": 12383, "pair": "ZEC/ETH", "price": 0.20663, "volume_percentage": 0.0026139149673656587, "rank": 366}, {"ticker_id": 23947, "pair": "DOCK/ETH", "price": 5.816e-05, "volume_percentage": 0.002567468019006846, "rank": 367}, {"ticker_id": 10326, "pair": "LRC/ETH", "price": 0.00018072, "volume_percentage": 0.0025327503385704966, "rank": 368}, {"ticker_id": 29968, "pair": "XLM/PAX", "price": 0.06659, "volume_percentage": 0.0025139567580981137, "rank": 369}, {"ticker_id": 21874, "pair": "THETA/BNB", "price": 0.004849, "volume_percentage": 0.0025127372661697188, "rank": 370}, {"ticker_id": 34242, "pair": "NEO/PAX", "price": 10.51, "volume_percentage": 0.0024956340711648505, "rank": 371}, {"ticker_id": 40735, "pair": "MFT/USDT", "price": 0.000986, "volume_percentage": 0.002445573668630432, "rank": 372}, {"ticker_id": 40710, "pair": "PERL/BNB", "price": 0.001378, "volume_percentage": 0.002417704010287279, "rank": 373}, {"ticker_id": 30360, "pair": "XLM/TUSD", "price": 0.06678, "volume_percentage": 0.002403217193965618, "rank": 374}, {"ticker_id": 32909, "pair": "USDS/USDT", "price": 0.9981, "volume_percentage": 0.0023713043846198285, "rank": 375}, {"ticker_id": 10685, "pair": "ETHOS/ETH", "price": 0.0002457, "volume_percentage": 0.0023702391180032457, "rank": 376}, {"ticker_id": 41698, "pair": "BAND/BNB", "price": 0.01554, "volume_percentage": 0.0023580985935003165, "rank": 377}, {"ticker_id": 30775, "pair": "ADA/TUSD", "price": 0.043, "volume_percentage": 0.0023575193740339386, "rank": 378}, {"ticker_id": 17609, "pair": "NCASH/ETH", "price": 5.09e-06, "volume_percentage": 0.0022977918149691486, "rank": 379}, {"ticker_id": 12751, "pair": "TNT/ETH", "price": 0.00037126, "volume_percentage": 0.0022968514765261934, "rank": 380}, {"ticker_id": 40560, "pair": "COCOS/BNB", "price": 4.55e-05, "volume_percentage": 0.002278363379621094, "rank": 381}, {"ticker_id": 43457, "pair": "LINK/BUSD", "price": 2.6866, "volume_percentage": 0.002252032165844752, "rank": 382}, {"ticker_id": 33344, "pair": "FET/BNB", "price": 0.001982, "volume_percentage": 0.002116290694548383, "rank": 383}, {"ticker_id": 30684, "pair": "XLM/USDC", "price": 0.06629, "volume_percentage": 0.0021098099963702, "rank": 384}, {"ticker_id": 14117, "pair": "BRD/BNB", "price": 0.01615, "volume_percentage": 0.0020985557377987338, "rank": 385}, {"ticker_id": 13164, "pair": "PPT/ETH", "price": 0.002899, "volume_percentage": 0.002094357303135269, "rank": 386}, {"ticker_id": 32943, "pair": "BTT/PAX", "price": 0.0004738, "volume_percentage": 0.0020926548492258513, "rank": 387}, {"ticker_id": 27711, "pair": "RVN/BNB", "price": 0.001444, "volume_percentage": 0.002091705390072747, "rank": 388}, {"ticker_id": 18032, "pair": "ZIL/BNB", "price": 0.0002661, "volume_percentage": 0.002055674225639954, "rank": 389}, {"ticker_id": 21818, "pair": "CVC/ETH", "price": 0.00022986, "volume_percentage": 0.0020445017969982354, "rank": 390}, {"ticker_id": 30361, "pair": "EOS/TUSD", "price": 3.347, "volume_percentage": 0.002033774558492204, "rank": 391}, {"ticker_id": 33239, "pair": "ZRX/BNB", "price": 0.01356, "volume_percentage": 0.0020250682588951172, "rank": 392}, {"ticker_id": 10873, "pair": "XVG/ETH", "price": 2.024e-05, "volume_percentage": 0.0019693446128143293, "rank": 393}, {"ticker_id": 13983, "pair": "AION/BNB", "price": 0.003735, "volume_percentage": 0.0019539000480518864, "rank": 394}, {"ticker_id": 38567, "pair": "GTO/USDT", "price": 0.01231, "volume_percentage": 0.0019449903721107554, "rank": 395}, {"ticker_id": 12017, "pair": "STORJ/ETH", "price": 0.0007609, "volume_percentage": 0.0019335949274990895, "rank": 396}, {"ticker_id": 22743, "pair": "KEY/ETH", "price": 7.4e-06, "volume_percentage": 0.001919903384592346, "rank": 397}, {"ticker_id": 12176, "pair": "RDN/ETH", "price": 0.00086, "volume_percentage": 0.0019022732848776444, "rank": 398}, {"ticker_id": 22099, "pair": "AGI/ETH", "price": 0.0001155, "volume_percentage": 0.0018973018199181732, "rank": 399}, {"ticker_id": 40730, "pair": "FUN/USDT", "price": 0.003221, "volume_percentage": 0.0018912560929680974, "rank": 400}]}
]